imka/__init__.py
imka/command.py
imka/configs.py
imka/file_provider.py
imka/frame.py
imka/frames.py
imka/hooks.py
imka/imka.py
imka/imka_config.py
imka/imka_configs.py
imka/mounts.py
imka/stack.py
imka/templates.py
imka/util.py
imka/values.py
imka-0.1.1.data/scripts/imka
imka-0.1.1.dist-info/LICENSE
imka-0.1.1.dist-info/METADATA
imka-0.1.1.dist-info/WHEEL
imka-0.1.1.dist-info/top_level.txt
imka-0.1.1.dist-info/RECORD
