Metadata-Version: 2.1
Name: imka
Version: 0.1.1
Summary: A docker swarm package manager
Home-page: https://github.com/byteplow/imka
Author: byteplow
Author-email: byteplow@posteo.de
License: MIT License
Project-URL: Source, https://github.com/byteplow/imka
Platform: UNKNOWN
License-File: LICENSE
Requires-Dist: click
Requires-Dist: dirhash
Requires-Dist: docker
Requires-Dist: Jinja2
Requires-Dist: pyaml
Requires-Dist: scp
Requires-Dist: paramiko
